yafti/__init__.py
yafti/__main__.py
yafti/abc.py
yafti/app.py
yafti/events.py
yafti/log.py
yafti/parser.py
yafti/plugin/flatpak.py
yafti/plugin/run.py
yafti/registry.py
yafti/screen/consent.py
yafti/screen/console.py
yafti/screen/dialog.py
yafti/screen/package/__init__.py
yafti/screen/package/models.py
yafti/screen/package/screen/__init__.py
yafti/screen/package/screen/install.py
yafti/screen/package/screen/package.py
yafti/screen/package/screen/picker.py
yafti/screen/package/state.py
yafti/screen/package/utils.py
yafti/screen/title.py
yafti/screen/utils.py
yafti/screen/window.py
yafti/setup.py
yafti/share.py
yafti-0.10.2.dist-info/LICENSE
yafti-0.10.2.dist-info/METADATA
yafti-0.10.2.dist-info/WHEEL
yafti-0.10.2.dist-info/entry_points.txt
yafti-0.10.2.dist-info/RECORD
