Metadata-Version: 2.1
Name: yafti
Version: 0.10.2
Summary: Yet another first time installer
Home-page: https://github.com/ublue-os/yafti
License: Apache 2.0
Author: Marco Ceppi
Author-email: marco@ceppi.net
Requires-Python: >=3.11,<4.0
Classifier: Environment :: X11 Applications :: GTK
Classifier: Framework :: AsyncIO
Classifier: Intended Audience :: End Users/Desktop
Classifier: License :: Other/Proprietary License
Classifier: Programming Language :: Python :: 3
Classifier: Programming Language :: Python :: 3.11
Classifier: Topic :: System :: Software Distribution
Requires-Dist: pydantic (>=2.8.2,<3.0.0)
Requires-Dist: pygobject (>=3.50.0,<4.0.0)
Requires-Dist: pyyaml (>=6.0,<7.0)
Requires-Dist: rich (>=13.3.2,<14.0.0)
Requires-Dist: typer (>=0.7)
Project-URL: Repository, https://github.com/ublue-os/yafti
